logyca_pagination/__init__.py
logyca_pagination/utils/__init__.py
logyca_pagination/utils/helpers/__init__.py
logyca_pagination/utils/helpers/pagination.py
logyca_pagination-0.1.2.dist-info/LICENSE.txt
logyca_pagination-0.1.2.dist-info/METADATA
logyca_pagination-0.1.2.dist-info/WHEEL
logyca_pagination-0.1.2.dist-info/top_level.txt
logyca_pagination-0.1.2.dist-info/RECORD
