Metadata-Version: 2.1
Name: logyca-pagination
Version: 0.1.2
Summary: An integration package created by the company LOGYCA to according to a query created with sqlalchemy, paginate its result and return the information in lists of items with page numbers that can be used in frontend grids.
Home-page: https://github.com/logyca/python-libraries/tree/main/logyca-pagination
Author: Jaime Andres Cardona Carrillo
Author-email: jacardona@outlook.com
License: MIT License
Keywords: pagination,serverless,backend,fastapi
Classifier: Development Status :: 4 - Beta
Classifier: Intended Audience :: Developers
Classifier: Intended Audience :: Information Technology
Classifier: Intended Audience :: System Administrators
Classifier: License :: OSI Approved :: MIT License
Classifier: Operating System :: OS Independent
Classifier: Programming Language :: Python :: 3 :: Only
Classifier: Programming Language :: Python :: 3.10
Classifier: Programming Language :: Python :: 3.11
Classifier: Programming Language :: Python :: 3.7
Classifier: Programming Language :: Python :: 3.8
Classifier: Programming Language :: Python :: 3.9
Classifier: Programming Language :: Python :: 3
Classifier: Programming Language :: Python
Classifier: Topic :: Database
Classifier: Topic :: Database :: Front-Ends
Classifier: Topic :: Software Development :: Libraries :: Python Modules
Classifier: Topic :: Software Development :: Libraries
Classifier: Topic :: Software Development
Classifier: Typing :: Typed
Requires-Python: >=3.8
License-File: LICENSE.txt
Requires-Dist: pydantic >=2.0.3
Requires-Dist: sqlalchemy >=2.0.6
